{
    "os": "Linux-6.8.0-55-generic-x86_64-with-glibc2.39",
    "python": "3.12.2",
    "heartbeatAt": "2025-05-28T20:07:27.687587",
    "startedAt": "2025-05-28T20:07:27.172422",
    "docker": null,
    "cuda": "9.0.176",
    "args": [],
    "state": "running",
    "program": "12tb_dsk3/SEIR_model/src/SEIR_kalmar_bleking.ipynb",
    "codePathLocal": null,
    "root": "/12tb_dsk3/SEIR_model",
    "git": {
        "remote": "https://github.com/danish2562022/SEIR_model.git",
        "commit": "815b8b500e481e3833db0d86f1dc04c90b7aa4bc"
    },
    "email": "danish2562022@gmail.com",
    "host": "polster",
    "username": "anwer",
    "executable": "/root/miniconda3/bin/python",
    "cpu_count": 16,
    "cpu_count_logical": 32,
    "cpu_freq": {
        "current": 4608.69925,
        "min": 545.0,
        "max": 5371.0
    },
    "cpu_freq_per_core": [
        {
            "current": 4640.138,
            "min": 545.0,
            "max": 5371.0
        },
        {
            "current": 4640.092,
            "min": 545.0,
            "max": 5371.0
        },
        {
            "current": 4640.092,
            "min": 545.0,
            "max": 5371.0
        },
        {
            "current": 4640.111,
            "min": 545.0,
            "max": 5371.0
        },
        {
            "current": 4640.101,
            "min": 545.0,
            "max": 5371.0
        },
        {
            "current": 4640.097,
            "min": 545.0,
            "max": 5371.0
        },
        {
            "current": 4640.097,
            "min": 545.0,
            "max": 5371.0
        },
        {
            "current": 4640.179,
            "min": 545.0,
            "max": 5371.0
        },
        {
            "current": 4630.273,
            "min": 545.0,
            "max": 5371.0
        },
        {
            "current": 4580.547,
            "min": 545.0,
            "max": 5371.0
        },
        {
            "current": 4580.562,
            "min": 545.0,
            "max": 5371.0
        },
        {
            "current": 4580.589,
            "min": 545.0,
            "max": 5371.0
        },
        {
            "current": 4580.543,
            "min": 545.0,
            "max": 5371.0
        },
        {
            "current": 4580.537,
            "min": 545.0,
            "max": 5371.0
        },
        {
            "current": 4580.556,
            "min": 545.0,
            "max": 5371.0
        },
        {
            "current": 4580.574,
            "min": 545.0,
            "max": 5371.0
        },
        {
            "current": 4649.537,
            "min": 545.0,
            "max": 5371.0
        },
        {
            "current": 4649.595,
            "min": 545.0,
            "max": 5371.0
        },
        {
            "current": 4649.571,
            "min": 545.0,
            "max": 5371.0
        },
        {
            "current": 4649.615,
            "min": 545.0,
            "max": 5371.0
        },
        {
            "current": 4649.549,
            "min": 545.0,
            "max": 5371.0
        },
        {
            "current": 4649.583,
            "min": 545.0,
            "max": 5371.0
        },
        {
            "current": 4649.563,
            "min": 545.0,
            "max": 5371.0
        },
        {
            "current": 4649.537,
            "min": 545.0,
            "max": 5371.0
        },
        {
            "current": 4580.552,
            "min": 545.0,
            "max": 5371.0
        },
        {
            "current": 4580.577,
            "min": 545.0,
            "max": 5371.0
        },
        {
            "current": 4580.586,
            "min": 545.0,
            "max": 5371.0
        },
        {
            "current": 4580.575,
            "min": 545.0,
            "max": 5371.0
        },
        {
            "current": 4580.581,
            "min": 545.0,
            "max": 5371.0
        },
        {
            "current": 4580.549,
            "min": 545.0,
            "max": 5371.0
        },
        {
            "current": 4580.582,
            "min": 545.0,
            "max": 5371.0
        },
        {
            "current": 4580.586,
            "min": 545.0,
            "max": 5371.0
        }
    ],
    "disk": {
        "/": {
            "total": 3752.004409790039,
            "used": 2783.7983894348145
        }
    },
    "gpu": "NVIDIA RTX 6000 Ada Generation",
    "gpu_count": 1,
    "gpu_devices": [
        {
            "name": "NVIDIA RTX 6000 Ada Generation",
            "memory_total": 51527024640
        }
    ],
    "memory": {
        "total": 251.08872985839844
    }
}
