{
    "os": "Linux-6.8.0-55-generic-x86_64-with-glibc2.39",
    "python": "3.12.2",
    "heartbeatAt": "2025-05-29T15:11:46.769912",
    "startedAt": "2025-05-29T15:11:46.223335",
    "docker": null,
    "cuda": "9.0.176",
    "args": [],
    "state": "running",
    "program": "12tb_dsk3/SEIR_model/src/SEIR_kalmar_bleking.ipynb",
    "codePathLocal": null,
    "root": "/12tb_dsk3/SEIR_model",
    "git": {
        "remote": "https://github.com/danish2562022/SEIR_model.git",
        "commit": "815b8b500e481e3833db0d86f1dc04c90b7aa4bc"
    },
    "email": "danish2562022@gmail.com",
    "host": "polster",
    "username": "anwer",
    "executable": "/root/miniconda3/bin/python",
    "cpu_count": 16,
    "cpu_count_logical": 32,
    "cpu_freq": {
        "current": 2623.0454062500003,
        "min": 545.0,
        "max": 5371.0
    },
    "cpu_freq_per_core": [
        {
            "current": 4774.993,
            "min": 545.0,
            "max": 5371.0
        },
        {
            "current": 4768.213,
            "min": 545.0,
            "max": 5371.0
        },
        {
            "current": 3111.153,
            "min": 545.0,
            "max": 5371.0
        },
        {
            "current": 2875.379,
            "min": 545.0,
            "max": 5371.0
        },
        {
            "current": 2480.43,
            "min": 545.0,
            "max": 5371.0
        },
        {
            "current": 545.0,
            "min": 545.0,
            "max": 5371.0
        },
        {
            "current": 545.0,
            "min": 545.0,
            "max": 5371.0
        },
        {
            "current": 1897.567,
            "min": 545.0,
            "max": 5371.0
        },
        {
            "current": 4788.579,
            "min": 545.0,
            "max": 5371.0
        },
        {
            "current": 4944.051,
            "min": 545.0,
            "max": 5371.0
        },
        {
            "current": 545.0,
            "min": 545.0,
            "max": 5371.0
        },
        {
            "current": 545.0,
            "min": 545.0,
            "max": 5371.0
        },
        {
            "current": 4773.821,
            "min": 545.0,
            "max": 5371.0
        },
        {
            "current": 3656.868,
            "min": 545.0,
            "max": 5371.0
        },
        {
            "current": 2866.755,
            "min": 545.0,
            "max": 5371.0
        },
        {
            "current": 5041.231,
            "min": 545.0,
            "max": 5371.0
        },
        {
            "current": 4768.184,
            "min": 545.0,
            "max": 5371.0
        },
        {
            "current": 545.0,
            "min": 545.0,
            "max": 5371.0
        },
        {
            "current": 545.0,
            "min": 545.0,
            "max": 5371.0
        },
        {
            "current": 545.0,
            "min": 545.0,
            "max": 5371.0
        },
        {
            "current": 545.0,
            "min": 545.0,
            "max": 5371.0
        },
        {
            "current": 545.0,
            "min": 545.0,
            "max": 5371.0
        },
        {
            "current": 545.0,
            "min": 545.0,
            "max": 5371.0
        },
        {
            "current": 545.0,
            "min": 545.0,
            "max": 5371.0
        },
        {
            "current": 2092.607,
            "min": 545.0,
            "max": 5371.0
        },
        {
            "current": 545.0,
            "min": 545.0,
            "max": 5371.0
        },
        {
            "current": 2474.765,
            "min": 545.0,
            "max": 5371.0
        },
        {
            "current": 3109.111,
            "min": 545.0,
            "max": 5371.0
        },
        {
            "current": 4703.829,
            "min": 545.0,
            "max": 5371.0
        },
        {
            "current": 545.0,
            "min": 545.0,
            "max": 5371.0
        },
        {
            "current": 2445.192,
            "min": 545.0,
            "max": 5371.0
        },
        {
            "current": 545.0,
            "min": 545.0,
            "max": 5371.0
        }
    ],
    "disk": {
        "/": {
            "total": 3752.004409790039,
            "used": 2783.8008155822754
        }
    },
    "gpu": "NVIDIA RTX 6000 Ada Generation",
    "gpu_count": 1,
    "gpu_devices": [
        {
            "name": "NVIDIA RTX 6000 Ada Generation",
            "memory_total": 51527024640
        }
    ],
    "memory": {
        "total": 251.08872985839844
    }
}
