{
    "os": "Linux-6.8.0-55-generic-x86_64-with-glibc2.39",
    "python": "3.12.2",
    "heartbeatAt": "2025-05-26T23:14:04.803064",
    "startedAt": "2025-05-26T23:14:04.317254",
    "docker": null,
    "cuda": "9.0.176",
    "args": [],
    "state": "running",
    "program": "12tb_dsk3/SEIR_model/src/SEIR_sthlm_so\u0308dermanland_oskar_danish-sweep_2.ipynb",
    "codePathLocal": null,
    "root": "/12tb_dsk3/SEIR_model",
    "git": {
        "remote": "https://github.com/danish2562022/SEIR_model.git",
        "commit": "815b8b500e481e3833db0d86f1dc04c90b7aa4bc"
    },
    "email": "danish2562022@gmail.com",
    "host": "polster",
    "username": "anwer",
    "executable": "/root/miniconda3/bin/python",
    "cpu_count": 16,
    "cpu_count_logical": 32,
    "cpu_freq": {
        "current": 1850.9959687500002,
        "min": 545.0,
        "max": 5371.0
    },
    "cpu_freq_per_core": [
        {
            "current": 4785.235,
            "min": 545.0,
            "max": 5371.0
        },
        {
            "current": 545.0,
            "min": 545.0,
            "max": 5371.0
        },
        {
            "current": 2950.439,
            "min": 545.0,
            "max": 5371.0
        },
        {
            "current": 1916.997,
            "min": 545.0,
            "max": 5371.0
        },
        {
            "current": 545.0,
            "min": 545.0,
            "max": 5371.0
        },
        {
            "current": 545.0,
            "min": 545.0,
            "max": 5371.0
        },
        {
            "current": 545.0,
            "min": 545.0,
            "max": 5371.0
        },
        {
            "current": 545.0,
            "min": 545.0,
            "max": 5371.0
        },
        {
            "current": 3401.72,
            "min": 545.0,
            "max": 5371.0
        },
        {
            "current": 4790.654,
            "min": 545.0,
            "max": 5371.0
        },
        {
            "current": 2624.484,
            "min": 545.0,
            "max": 5371.0
        },
        {
            "current": 2618.079,
            "min": 545.0,
            "max": 5371.0
        },
        {
            "current": 3437.827,
            "min": 545.0,
            "max": 5371.0
        },
        {
            "current": 2987.075,
            "min": 545.0,
            "max": 5371.0
        },
        {
            "current": 545.0,
            "min": 545.0,
            "max": 5371.0
        },
        {
            "current": 4999.612,
            "min": 545.0,
            "max": 5371.0
        },
        {
            "current": 545.0,
            "min": 545.0,
            "max": 5371.0
        },
        {
            "current": 545.0,
            "min": 545.0,
            "max": 5371.0
        },
        {
            "current": 545.0,
            "min": 545.0,
            "max": 5371.0
        },
        {
            "current": 545.0,
            "min": 545.0,
            "max": 5371.0
        },
        {
            "current": 545.0,
            "min": 545.0,
            "max": 5371.0
        },
        {
            "current": 545.0,
            "min": 545.0,
            "max": 5371.0
        },
        {
            "current": 545.0,
            "min": 545.0,
            "max": 5371.0
        },
        {
            "current": 545.0,
            "min": 545.0,
            "max": 5371.0
        },
        {
            "current": 545.0,
            "min": 545.0,
            "max": 5371.0
        },
        {
            "current": 545.0,
            "min": 545.0,
            "max": 5371.0
        },
        {
            "current": 545.0,
            "min": 545.0,
            "max": 5371.0
        },
        {
            "current": 545.0,
            "min": 545.0,
            "max": 5371.0
        },
        {
            "current": 545.0,
            "min": 545.0,
            "max": 5371.0
        },
        {
            "current": 545.0,
            "min": 545.0,
            "max": 5371.0
        },
        {
            "current": 3796.934,
            "min": 545.0,
            "max": 5371.0
        },
        {
            "current": 2186.65,
            "min": 545.0,
            "max": 5371.0
        }
    ],
    "disk": {
        "/": {
            "total": 3752.004409790039,
            "used": 2783.746105194092
        }
    },
    "gpu": "NVIDIA RTX 6000 Ada Generation",
    "gpu_count": 1,
    "gpu_devices": [
        {
            "name": "NVIDIA RTX 6000 Ada Generation",
            "memory_total": 51527024640
        }
    ],
    "memory": {
        "total": 251.08872985839844
    }
}
