{
    "os": "Linux-6.8.0-55-generic-x86_64-with-glibc2.39",
    "python": "3.12.2",
    "heartbeatAt": "2025-05-29T12:50:07.925717",
    "startedAt": "2025-05-29T12:50:07.406815",
    "docker": null,
    "cuda": "9.0.176",
    "args": [],
    "state": "running",
    "program": "12tb_dsk3/SEIR_model/src/SEIR_kalmar_bleking.ipynb",
    "codePathLocal": null,
    "root": "/12tb_dsk3/SEIR_model",
    "git": {
        "remote": "https://github.com/danish2562022/SEIR_model.git",
        "commit": "815b8b500e481e3833db0d86f1dc04c90b7aa4bc"
    },
    "email": "danish2562022@gmail.com",
    "host": "polster",
    "username": "anwer",
    "executable": "/root/miniconda3/bin/python",
    "cpu_count": 16,
    "cpu_count_logical": 32,
    "cpu_freq": {
        "current": 1924.1696875000002,
        "min": 545.0,
        "max": 5371.0
    },
    "cpu_freq_per_core": [
        {
            "current": 545.0,
            "min": 545.0,
            "max": 5371.0
        },
        {
            "current": 545.0,
            "min": 545.0,
            "max": 5371.0
        },
        {
            "current": 545.0,
            "min": 545.0,
            "max": 5371.0
        },
        {
            "current": 545.0,
            "min": 545.0,
            "max": 5371.0
        },
        {
            "current": 545.0,
            "min": 545.0,
            "max": 5371.0
        },
        {
            "current": 545.0,
            "min": 545.0,
            "max": 5371.0
        },
        {
            "current": 545.0,
            "min": 545.0,
            "max": 5371.0
        },
        {
            "current": 545.0,
            "min": 545.0,
            "max": 5371.0
        },
        {
            "current": 4765.915,
            "min": 545.0,
            "max": 5371.0
        },
        {
            "current": 4791.354,
            "min": 545.0,
            "max": 5371.0
        },
        {
            "current": 4765.065,
            "min": 545.0,
            "max": 5371.0
        },
        {
            "current": 545.0,
            "min": 545.0,
            "max": 5371.0
        },
        {
            "current": 2704.911,
            "min": 545.0,
            "max": 5371.0
        },
        {
            "current": 3125.088,
            "min": 545.0,
            "max": 5371.0
        },
        {
            "current": 1885.563,
            "min": 545.0,
            "max": 5371.0
        },
        {
            "current": 1839.08,
            "min": 545.0,
            "max": 5371.0
        },
        {
            "current": 4778.626,
            "min": 545.0,
            "max": 5371.0
        },
        {
            "current": 3266.922,
            "min": 545.0,
            "max": 5371.0
        },
        {
            "current": 545.0,
            "min": 545.0,
            "max": 5371.0
        },
        {
            "current": 545.0,
            "min": 545.0,
            "max": 5371.0
        },
        {
            "current": 4790.178,
            "min": 545.0,
            "max": 5371.0
        },
        {
            "current": 545.0,
            "min": 545.0,
            "max": 5371.0
        },
        {
            "current": 545.0,
            "min": 545.0,
            "max": 5371.0
        },
        {
            "current": 545.0,
            "min": 545.0,
            "max": 5371.0
        },
        {
            "current": 545.0,
            "min": 545.0,
            "max": 5371.0
        },
        {
            "current": 545.0,
            "min": 545.0,
            "max": 5371.0
        },
        {
            "current": 545.0,
            "min": 545.0,
            "max": 5371.0
        },
        {
            "current": 3596.079,
            "min": 545.0,
            "max": 5371.0
        },
        {
            "current": 545.0,
            "min": 545.0,
            "max": 5371.0
        },
        {
            "current": 545.0,
            "min": 545.0,
            "max": 5371.0
        },
        {
            "current": 4056.45,
            "min": 545.0,
            "max": 5371.0
        },
        {
            "current": 2353.606,
            "min": 545.0,
            "max": 5371.0
        }
    ],
    "disk": {
        "/": {
            "total": 3752.004409790039,
            "used": 2783.8005142211914
        }
    },
    "gpu": "NVIDIA RTX 6000 Ada Generation",
    "gpu_count": 1,
    "gpu_devices": [
        {
            "name": "NVIDIA RTX 6000 Ada Generation",
            "memory_total": 51527024640
        }
    ],
    "memory": {
        "total": 251.08872985839844
    }
}
