{
    "os": "Linux-6.8.0-55-generic-x86_64-with-glibc2.39",
    "python": "3.12.2",
    "heartbeatAt": "2025-05-29T14:54:00.724785",
    "startedAt": "2025-05-29T14:54:00.082599",
    "docker": null,
    "cuda": "9.0.176",
    "args": [],
    "state": "running",
    "program": "12tb_dsk3/SEIR_model/src/SEIR_skane_kronoberg.ipynb",
    "codePathLocal": null,
    "root": "/12tb_dsk3/SEIR_model",
    "git": {
        "remote": "https://github.com/danish2562022/SEIR_model.git",
        "commit": "815b8b500e481e3833db0d86f1dc04c90b7aa4bc"
    },
    "email": "danish2562022@gmail.com",
    "host": "polster",
    "username": "anwer",
    "executable": "/root/miniconda3/bin/python",
    "cpu_count": 16,
    "cpu_count_logical": 32,
    "cpu_freq": {
        "current": 2180.7798749999997,
        "min": 545.0,
        "max": 5371.0
    },
    "cpu_freq_per_core": [
        {
            "current": 3385.658,
            "min": 545.0,
            "max": 5371.0
        },
        {
            "current": 4975.323,
            "min": 545.0,
            "max": 5371.0
        },
        {
            "current": 2886.59,
            "min": 545.0,
            "max": 5371.0
        },
        {
            "current": 3046.203,
            "min": 545.0,
            "max": 5371.0
        },
        {
            "current": 4787.966,
            "min": 545.0,
            "max": 5371.0
        },
        {
            "current": 2876.256,
            "min": 545.0,
            "max": 5371.0
        },
        {
            "current": 4763.884,
            "min": 545.0,
            "max": 5371.0
        },
        {
            "current": 3667.104,
            "min": 545.0,
            "max": 5371.0
        },
        {
            "current": 545.0,
            "min": 545.0,
            "max": 5371.0
        },
        {
            "current": 545.0,
            "min": 545.0,
            "max": 5371.0
        },
        {
            "current": 545.0,
            "min": 545.0,
            "max": 5371.0
        },
        {
            "current": 545.0,
            "min": 545.0,
            "max": 5371.0
        },
        {
            "current": 545.0,
            "min": 545.0,
            "max": 5371.0
        },
        {
            "current": 2569.151,
            "min": 545.0,
            "max": 5371.0
        },
        {
            "current": 4782.505,
            "min": 545.0,
            "max": 5371.0
        },
        {
            "current": 545.0,
            "min": 545.0,
            "max": 5371.0
        },
        {
            "current": 545.0,
            "min": 545.0,
            "max": 5371.0
        },
        {
            "current": 545.0,
            "min": 545.0,
            "max": 5371.0
        },
        {
            "current": 545.0,
            "min": 545.0,
            "max": 5371.0
        },
        {
            "current": 545.0,
            "min": 545.0,
            "max": 5371.0
        },
        {
            "current": 545.0,
            "min": 545.0,
            "max": 5371.0
        },
        {
            "current": 545.0,
            "min": 545.0,
            "max": 5371.0
        },
        {
            "current": 545.0,
            "min": 545.0,
            "max": 5371.0
        },
        {
            "current": 4706.821,
            "min": 545.0,
            "max": 5371.0
        },
        {
            "current": 545.0,
            "min": 545.0,
            "max": 5371.0
        },
        {
            "current": 2912.547,
            "min": 545.0,
            "max": 5371.0
        },
        {
            "current": 4782.28,
            "min": 545.0,
            "max": 5371.0
        },
        {
            "current": 545.0,
            "min": 545.0,
            "max": 5371.0
        },
        {
            "current": 545.0,
            "min": 545.0,
            "max": 5371.0
        },
        {
            "current": 545.0,
            "min": 545.0,
            "max": 5371.0
        },
        {
            "current": 545.0,
            "min": 545.0,
            "max": 5371.0
        },
        {
            "current": 545.0,
            "min": 545.0,
            "max": 5371.0
        }
    ],
    "disk": {
        "/": {
            "total": 3752.004409790039,
            "used": 2783.8008041381836
        }
    },
    "gpu": "NVIDIA RTX 6000 Ada Generation",
    "gpu_count": 1,
    "gpu_devices": [
        {
            "name": "NVIDIA RTX 6000 Ada Generation",
            "memory_total": 51527024640
        }
    ],
    "memory": {
        "total": 251.08872985839844
    }
}
