{
    "os": "Linux-6.8.0-55-generic-x86_64-with-glibc2.39",
    "python": "3.12.2",
    "heartbeatAt": "2025-05-27T12:35:27.028631",
    "startedAt": "2025-05-27T12:35:26.520899",
    "docker": null,
    "cuda": "9.0.176",
    "args": [],
    "state": "running",
    "program": "12tb_dsk3/SEIR_model/src/SEIR_sthlm_so\u0308dermanland_os_da_sweep_2.ipynb",
    "codePathLocal": null,
    "root": "/12tb_dsk3/SEIR_model",
    "git": {
        "remote": "https://github.com/danish2562022/SEIR_model.git",
        "commit": "815b8b500e481e3833db0d86f1dc04c90b7aa4bc"
    },
    "email": "danish2562022@gmail.com",
    "host": "polster",
    "username": "anwer",
    "executable": "/root/miniconda3/bin/python",
    "cpu_count": 16,
    "cpu_count_logical": 32,
    "cpu_freq": {
        "current": 2038.16453125,
        "min": 545.0,
        "max": 5371.0
    },
    "cpu_freq_per_core": [
        {
            "current": 4774.656,
            "min": 545.0,
            "max": 5371.0
        },
        {
            "current": 545.0,
            "min": 545.0,
            "max": 5371.0
        },
        {
            "current": 4721.952,
            "min": 545.0,
            "max": 5371.0
        },
        {
            "current": 545.0,
            "min": 545.0,
            "max": 5371.0
        },
        {
            "current": 4716.971,
            "min": 545.0,
            "max": 5371.0
        },
        {
            "current": 1893.514,
            "min": 545.0,
            "max": 5371.0
        },
        {
            "current": 1880.574,
            "min": 545.0,
            "max": 5371.0
        },
        {
            "current": 1877.681,
            "min": 545.0,
            "max": 5371.0
        },
        {
            "current": 4767.97,
            "min": 545.0,
            "max": 5371.0
        },
        {
            "current": 545.0,
            "min": 545.0,
            "max": 5371.0
        },
        {
            "current": 545.0,
            "min": 545.0,
            "max": 5371.0
        },
        {
            "current": 545.0,
            "min": 545.0,
            "max": 5371.0
        },
        {
            "current": 2880.442,
            "min": 545.0,
            "max": 5371.0
        },
        {
            "current": 545.0,
            "min": 545.0,
            "max": 5371.0
        },
        {
            "current": 4792.341,
            "min": 545.0,
            "max": 5371.0
        },
        {
            "current": 545.0,
            "min": 545.0,
            "max": 5371.0
        },
        {
            "current": 545.0,
            "min": 545.0,
            "max": 5371.0
        },
        {
            "current": 545.0,
            "min": 545.0,
            "max": 5371.0
        },
        {
            "current": 545.0,
            "min": 545.0,
            "max": 5371.0
        },
        {
            "current": 2786.259,
            "min": 545.0,
            "max": 5371.0
        },
        {
            "current": 545.0,
            "min": 545.0,
            "max": 5371.0
        },
        {
            "current": 545.0,
            "min": 545.0,
            "max": 5371.0
        },
        {
            "current": 545.0,
            "min": 545.0,
            "max": 5371.0
        },
        {
            "current": 3147.804,
            "min": 545.0,
            "max": 5371.0
        },
        {
            "current": 545.0,
            "min": 545.0,
            "max": 5371.0
        },
        {
            "current": 545.0,
            "min": 545.0,
            "max": 5371.0
        },
        {
            "current": 545.0,
            "min": 545.0,
            "max": 5371.0
        },
        {
            "current": 545.0,
            "min": 545.0,
            "max": 5371.0
        },
        {
            "current": 545.0,
            "min": 545.0,
            "max": 5371.0
        },
        {
            "current": 2836.501,
            "min": 545.0,
            "max": 5371.0
        },
        {
            "current": 545.0,
            "min": 545.0,
            "max": 5371.0
        },
        {
            "current": 2990.83,
            "min": 545.0,
            "max": 5371.0
        }
    ],
    "disk": {
        "/": {
            "total": 3752.004409790039,
            "used": 2783.787326812744
        }
    },
    "gpu": "NVIDIA RTX 6000 Ada Generation",
    "gpu_count": 1,
    "gpu_devices": [
        {
            "name": "NVIDIA RTX 6000 Ada Generation",
            "memory_total": 51527024640
        }
    ],
    "memory": {
        "total": 251.08872985839844
    }
}
